finetuner_commons-0.13.10-nspkg.pth
_finetuner/data/__init__.py
_finetuner/data/collate.py
_finetuner/data/preprocess.py
_finetuner/data/utils.py
_finetuner/models/__init__.py
_finetuner/models/builders.py
_finetuner/models/export.py
_finetuner/models/inference.py
_finetuner/models/load.py
_finetuner/models/poolers.py
_finetuner/models/utils.py
_finetuner/models/nn/__init__.py
_finetuner/models/nn/modules.py
_finetuner/models/nn/pointnet.py
_finetuner/models/nn/wiseft.py
_finetuner/runner/__init__.py
_finetuner/runner/artifact.py
_finetuner/runner/helper.py
_finetuner/runner/model.py
_finetuner/tailor/__init__.py
_finetuner/tailor/display.py
_finetuner/tailor/projection.py
_finetuner/tailor/tailor.py
finetuner_commons-0.13.10.dist-info/METADATA
finetuner_commons-0.13.10.dist-info/WHEEL
finetuner_commons-0.13.10.dist-info/namespace_packages.txt
finetuner_commons-0.13.10.dist-info/top_level.txt
finetuner_commons-0.13.10.dist-info/RECORD
