Metadata-Version: 2.1
Name: finetuner-commons
Version: 0.13.10
Summary: The finetuner-commons package provides common functionality between core and client.
Home-page: https://github.com/jina-ai/finetuner.fit/
Author: Jina AI
Author-email: team-finetuner@jina.ai
License: Proprietary
Download-URL: https://github.com/jina-ai/finetuner.fit/tags
Project-URL: Source, https://github.com/jina-ai/finetuner.fit/
Project-URL: Tracker, https://github.com/jina-ai/finetuner.fit/issues
Keywords: jina neural-search neural-network deep-learning pretraining fine-tuning pretrained-models triplet-loss metric-learning siamese-network few-shot-learning
Platform: UNKNOWN
Classifier: Development Status :: 5 - Production/Stable
Classifier: Intended Audience :: Developers
Classifier: Intended Audience :: Education
Classifier: Intended Audience :: Science/Research
Classifier: Programming Language :: Python :: 3.8
Classifier: Programming Language :: Python :: 3.9
Classifier: Environment :: Console
Classifier: Operating System :: OS Independent
Classifier: Topic :: Scientific/Engineering :: Artificial Intelligence
Requires-Python: >=3.8.0
Requires-Dist: docarray[common] (<0.30.0)
Requires-Dist: jina-hubble-sdk (>=0.33.1)
Requires-Dist: onnx (>1.11.0)
Requires-Dist: onnxruntime (>1.11.1)
Requires-Dist: open-clip-torch (==2.20.0)
Requires-Dist: rich (>=12.4.4)
Requires-Dist: torchvision (~=0.15.2)
Requires-Dist: torch (~=2.0.1)
Requires-Dist: transformers (==4.20.1)
